ssd_0_to_9/ssd_0_to_9.srcs/sources_1/new/pmod_ssd.v
`timescale 1ns / 1ps
//////////////////////////////////////////////////////////////////////////////////
// Company: SSU
// Engineer: Anthjony Meyer Slechta
// 
// Create Date: 08/25/2025 05:01:42 PM
// Design Name: 
// Module Name: pmod_ssd
// Project Name: Seven Segment LED Display Counter (PMOD)
// Target Devices: PYNQ-Z2
// Tool Versions: 
// Description: 0-9 loop utilizing a seven segment display (PMOD). Timer count needs
//              to be set to 5 for TB, otherwise 50_000_000.
// 
// Dependencies: 
// 
// Revision:
// Revision 0.01 - File Created
// Additional Comments:
// 
//////////////////////////////////////////////////////////////////////////////////


module pmod_ssd(
    input sys_clk,
    input rst_n,
    output reg[6:0] ssd,
    output sel
);

    reg[31:0] timer_cnt;
    reg[3:0] binary_cnt;
    
    assign sel = 0;
    
    // Seven Seg MUX
    // Had to put in module or it would fail during simulation
    function [6:0] seven_seg;
        input [3:0] binary_cnt;
        case(binary_cnt)
            4'd0: seven_seg = 7'b1111110;
            4'd1: seven_seg = 7'b0110000;
            4'd2: seven_seg = 7'b1101101;
            4'd3: seven_seg = 7'b1111001;
            4'd4: seven_seg = 7'b0110011;
            4'd5: seven_seg = 7'b1011011;
            4'd6: seven_seg = 7'b0011111;
            4'd7: seven_seg = 7'b1110000;
            4'd8: seven_seg = 7'b1111111;
            4'd9: seven_seg = 7'b1111011;
            default: seven_seg = 7'b0000000;
        endcase    
    endfunction
    
    always@(posedge sys_clk or negedge rst_n)
    begin
        if(!rst_n)
        begin
            //ssd <= 7'b1111110;

            binary_cnt <= 4'b0000;

            timer_cnt <= 32'd0;
            
            ssd <= seven_seg(binary_cnt);
        end
        else if(binary_cnt >= 4'b1001 && timer_cnt >= 32'd5)
        begin
            // If binary count is greater than 0, and the delay has been long enough
            //      reset the binary counter, and timer counter.
            binary_cnt <= 4'b0000;

            timer_cnt <= 32'd0;
            
            ssd <= seven_seg(binary_cnt);
        end
        else if(timer_cnt >= 32'd5)
        begin
            binary_cnt <= binary_cnt + 1;

            timer_cnt <= 32'd0;
            
            ssd <= seven_seg(binary_cnt);
        end
        else
        begin

            ssd <= seven_seg(binary_cnt);
            timer_cnt <= timer_cnt + 32'd1;
        end
        // Tried with having this being the only place ssd was updated
        //      But it would not compile, not sure why.
       // ssd <= seven_seg(binary_cnt);
    end
endmodule

ssd_0_to_9/ssd_0_to_9.srcs/sim_1/new/tb_pmod_ssd.v
`timescale 1ns / 1ps
//////////////////////////////////////////////////////////////////////////////////
// Company: SSU
// Engineer: Anthony Meyer Slechta
// 
// Create Date: 08/27/2025 05:43:52 PM
// Design Name: 
// Module Name: pmod_ssd_tb
// Project Name: Seven Segment LED Display Counter (PMOD)
// Target Devices: PYNQ-Z2
// Tool Versions: 
// Description: Simple testbench just showing continuous loop of SSD.
//              Timer count need to be set to 5 max to show up.
//
// Dependencies: 
// 
// Revision:
// Revision 0.01 - File Created
// Additional Comments:
// 
//////////////////////////////////////////////////////////////////////////////////

module tb_pmod_ssd;
    reg sys_clk;
    reg rst_n;
    wire [6:0] ssd;
    wire sel;

    // Instantiate the DUT (copied from previous tb files)
    pmod_ssd uut (
        .sys_clk(sys_clk),
        .rst_n(rst_n),
        .ssd(ssd),
        .sel(sel)
    );

    // Clock generation: 10ns period = 100MHz
    initial sys_clk = 0;
    always #5 sys_clk = ~sys_clk;

    // Stimulus
    initial begin
        // Test Reset
        rst_n = 0;
        #50;
        rst_n = 1;

        // Let sim run long enough to show a continuous loop 
        #1000_000;

        $finish;
    end

    // Output
    initial begin
        $display("Time\tReset\t\tSSD");
        $monitor("%0t\t%b\t\t%07b", $time, rst_n, ssd);
    end

endmodule

ssd_0_to_9/ssd_0_to_9.sim/sim_1/behav/xsim/tb_pmod_ssd.vcd
$date
   Wed Aug 27 17:57:00 2025
$end
$version
  2022.2
$end
$timescale
  1ps
$end
$scope module tb_pmod_ssd $end
$var reg 1 ! sys_clk $end
$var reg 1 " rst_n $end
$var wire 7 # ssd [6:0] $end
$var wire 1 $ sel $end
$scope module uut $end
$var wire 1 % sys_clk $end
$var wire 1 & rst_n $end
$var reg 7 ' ssd [6:0] $end
$var wire 1 $ sel $end
$var reg 32 ( timer_cnt [31:0] $end
$var reg 4 ) binary_cnt [3:0] $end
$scope function seven_seg $end
$var reg 7 * seven_seg [6:0] $end
$var reg 4 + binary_cnt [3:0] $end
$upscope $end
$upscope $end
$upscope $end
$enddefinitions $end
#0
$dumpvars
0!
0"
b0 #
0$
0%
0&
b0 '
b0 (
b0 )
b0 *
bx +
$end
#5000
1!
b1111110 #
1%
b1111110 '
b1111110 *
b0 +
#10000
0!
0%
#15000
1!
1%
#20000
0!
0%
#25000
1!
1%
#30000
0!
0%
#35000
1!
1%
#40000
0!
0%
#45000
1!
1%
#50000
0!
1"
0%
1&
#55000
1!
1%
b1 (
#60000
0!
0%
#65000
1!
1%
b10 (
#70000
0!
0%
#75000
1!
1%
b11 (
#80000
0!
0%
#85000
1!
1%
b100 (
#90000
0!
0%
#95000
1!
1%
b101 (
#100000
0!
0%
#105000
1!
1%
b0 (
b1 )
#110000
0!
0%
#115000
1!
b110000 #
1%
b110000 '
b1 (
b110000 *
b1 +
#120000
0!
0%
#125000
1!
1%
b10 (
#130000
0!
0%
#135000
1!
1%
b11 (
#140000
0!
0%
#145000
1!
1%
b100 (
#150000
0!
0%
#155000
1!
1%
b101 (
#160000
0!
0%
#165000
1!
1%
b0 (
b10 )
#170000
0!
0%
#175000
1!
b1101101 #
1%
b1101101 '
b1 (
b1101101 *
b10 +
#180000
0!
0%
#185000
1!
1%
b10 (
#190000
0!
0%
#195000
1!
1%
b11 (
#200000
0!
0%
#205000
1!
1%
b100 (
#210000
0!
0%
#215000
1!
1%
b101 (
#220000
0!
0%
#225000
1!
1%
b0 (
b11 )
#230000
0!
0%
#235000
1!
b1111001 #
1%
b1111001 '
b1 (
b1111001 *
b11 +
#240000
0!
0%
#245000
1!
1%
b10 (
#250000
0!
0%
#255000
1!
1%
b11 (
#260000
0!
0%
#265000
1!
1%
b100 (
#270000
0!
0%
#275000
1!
1%
b101 (
#280000
0!
0%
#285000
1!
1%
b0 (
b100 )
#290000
0!
0%
#295000
1!
b110011 #
1%
b110011 '
b1 (
b110011 *
b100 +
#300000
0!
0%
#305000
1!
1%
b10 (
#310000
0!
0%
#315000
1!
1%
b11 (
#320000
0!
0%
#325000
1!
1%
b100 (
#330000
0!
0%
#335000
1!
1%
b101 (
#340000
0!
0%
#345000
1!
1%
b0 (
b101 )
#350000
0!
0%
#355000
1!
b1011011 #
1%
b1011011 '
b1 (
b1011011 *
b101 +
#360000
0!
0%
#365000
1!
1%
b10 (
#370000
0!
0%
#375000
1!
1%
b11 (
#380000
0!
0%
#385000
1!
1%
b100 (
#390000
0!
0%
#395000
1!
1%
b101 (
#400000
0!
0%
#405000
1!
1%
b0 (
b110 )
#410000
0!
0%
#415000
1!
b11111 #
1%
b11111 '
b1 (
b11111 *
b110 +
#420000
0!
0%
#425000
1!
1%
b10 (
#430000
0!
0%
#435000
1!
1%
b11 (
#440000
0!
0%
#445000
1!
1%
b100 (
#450000
0!
0%
#455000
1!
1%
b101 (
#460000
0!
0%
#465000
1!
1%
b0 (
b111 )
#470000
0!
0%
#475000
1!
b1110000 #
1%
b1110000 '
b1 (
b1110000 *
b111 +
#480000
0!
0%
#485000
1!
1%
b10 (
#490000
0!
0%
#495000
1!
1%
b11 (
#500000
0!
0%
#505000
1!
1%
b100 (
#510000
0!
0%
#515000
1!
1%
b101 (
#520000
0!
0%
#525000
1!
1%
b0 (
b1000 )
#530000
0!
0%
#535000
1!
b1111111 #
1%
b1111111 '
b1 (
b1111111 *
b1000 +
#540000
0!
0%
#545000
1!
1%
b10 (
#550000
0!
0%
#555000
1!
1%
b11 (
#560000
0!
0%
#565000
1!
1%
b100 (
#570000
0!
0%
#575000
1!
1%
b101 (
#580000
0!
0%
#585000
1!
1%
b0 (
b1001 )
#590000
0!
0%
#595000
1!
b1111011 #
1%
b1111011 '
b1 (
b1111011 *
b1001 +
#600000
0!
0%
#605000
1!
1%
b10 (
#610000
0!
0%
#615000
1!
1%
b11 (
#620000
0!
0%
#625000
1!
1%
b100 (
#630000
0!
0%
#635000
1!
1%
b101 (
#640000
0!
0%
#645000
1!
1%
b0 (
b1010 )
#650000
0!
0%
#655000
1!
b0 #
1%
b0 '
b1 (
b0 *
b1010 +
#660000
0!
0%
#665000
1!
1%
b10 (
#670000
0!
0%
#675000
1!
1%
b11 (
#680000
0!
0%
#685000
1!
1%
b100 (
#690000
0!
0%
#695000
1!
1%
b101 (
#700000
0!
0%
#705000
1!
1%
b0 (
b0 )
#710000
0!
0%
#715000
1!
b1111110 #
1%
b1111110 '
b1 (
b1111110 *
b0 +
#720000
0!
0%
#725000
1!
1%
b10 (
#730000
0!
0%
#735000
1!
1%
b11 (
#740000
0!
0%
#745000
1!
1%
b100 (
#750000
0!
0%
#755000
1!
1%
b101 (
#760000
0!
0%
#765000
1!
1%
b0 (
b1 )
#770000
0!
0%
#775000
1!
b110000 #
1%
b110000 '
b1 (
b110000 *
b1 +
#780000
0!
0%
#785000
1!
1%
b10 (
#790000
0!
0%
#795000
1!
1%
b11 (
#800000
0!
0%
#805000
1!
1%
b100 (
#810000
0!
0%
#815000
1!
1%
b101 (
#820000
0!
0%
#825000
1!
1%
b0 (
b10 )
#830000
0!
0%
#835000
1!
b1101101 #
1%
b1101101 '
b1 (
b1101101 *
b10 +
#840000
0!
0%
#845000
1!
1%
b10 (
#850000
0!
0%
#855000
1!
1%
b11 (
#860000
0!
0%
#865000
1!
1%
b100 (
#870000
0!
0%
#875000
1!
1%
b101 (
#880000
0!
0%
#885000
1!
1%
b0 (
b11 )
#890000
0!
0%
#895000
1!
b1111001 #
1%
b1111001 '
b1 (
b1111001 *
b11 +
#900000
0!
0%
#905000
1!
1%
b10 (
#910000
0!
0%
#915000
1!
1%
b11 (
#920000
0!
0%
#925000
1!
1%
b100 (
#930000
0!
0%
#935000
1!
1%
b101 (
#940000
0!
0%
#945000
1!
1%
b0 (
b100 )
#950000
0!
0%
#955000
1!
b110011 #
1%
b110011 '
b1 (
b110011 *
b100 +
#960000
0!
0%
#965000
1!
1%
b10 (
#970000
0!
0%
#975000
1!
1%
b11 (
#980000
0!
0%
#985000
1!
1%
b100 (
#990000
0!
0%
#995000
1!
1%
b101 (
